django_static_markdown_blog/__init__.py
django_static_markdown_blog/admin.py
django_static_markdown_blog/apps.py
django_static_markdown_blog/core/__init__.py
django_static_markdown_blog/core/builders.py
django_static_markdown_blog/core/cache.py
django_static_markdown_blog/core/exceptions.py
django_static_markdown_blog/core/models.py
django_static_markdown_blog/core/utils.py
django_static_markdown_blog/migrations/__init__.py
django_static_markdown_blog/models.py
django_static_markdown_blog/settings.py
django_static_markdown_blog/static/blog/css/highlight-js/a11y-dark.css
django_static_markdown_blog/static/blog/css/highlight-js/a11y-light.css
django_static_markdown_blog/static/blog/css/highlight-js/agate.css
django_static_markdown_blog/static/blog/css/highlight-js/an-old-hope.css
django_static_markdown_blog/static/blog/css/highlight-js/androidstudio.css
django_static_markdown_blog/static/blog/css/highlight-js/arduino-light.css
django_static_markdown_blog/static/blog/css/highlight-js/arta.css
django_static_markdown_blog/static/blog/css/highlight-js/ascetic.css
django_static_markdown_blog/static/blog/css/highlight-js/atelier-cave-dark.css
django_static_markdown_blog/static/blog/css/highlight-js/atelier-cave-light.css
django_static_markdown_blog/static/blog/css/highlight-js/atelier-dune-dark.css
django_static_markdown_blog/static/blog/css/highlight-js/atelier-dune-light.css
django_static_markdown_blog/static/blog/css/highlight-js/atelier-estuary-dark.css
django_static_markdown_blog/static/blog/css/highlight-js/atelier-estuary-light.css
django_static_markdown_blog/static/blog/css/highlight-js/atelier-forest-dark.css
django_static_markdown_blog/static/blog/css/highlight-js/atelier-forest-light.css
django_static_markdown_blog/static/blog/css/highlight-js/atelier-heath-dark.css
django_static_markdown_blog/static/blog/css/highlight-js/atelier-heath-light.css
django_static_markdown_blog/static/blog/css/highlight-js/atelier-lakeside-dark.css
django_static_markdown_blog-0.1.2.dist-info/WHEEL
django_static_markdown_blog-0.1.2.dist-info/METADATA
django_static_markdown_blog-0.1.2.dist-info/RECORD
