Metadata-Version: 2.1
Name: django-static-markdown-blog
Version: 0.1.2
Summary: Django application to create a blog based on local Markdown files
Home-page: https://gitlab.com/aloha68/django-static-markdown-blog
License: ISC
Author: Aloha68
Author-email: dev@aloha.im
Requires-Python: >=3.5,<4.0
Classifier: License :: OSI Approved
Classifier: Programming Language :: Python :: 3
Classifier: Programming Language :: Python :: 3.5
Classifier: Programming Language :: Python :: 3.6
Classifier: Programming Language :: Python :: 3.7
Requires-Dist: beautifulsoup4 (>=4.6,<5.0)
Requires-Dist: django (>=2.2,<3.0)
Requires-Dist: django-leaflet-gpx (>=0.1,<0.2)
Requires-Dist: markdown (>=2.6,<3.0)
Requires-Dist: redis (>=2.10,<3.0)
Project-URL: Repository, https://gitlab.com/aloha68/django-static-markdown-blog
